config/__init__.py
config/settings.py
config/urls.py
netkeiba/__init__.py
netkeiba/apps.py
netkeiba/argtype.py
netkeiba/items.py
netkeiba/middlewares.py
netkeiba/pipelines.py
netkeiba/settings.py
netkeiba/user_agents.txt
netkeiba/management/__init__.py
netkeiba/management/commands/__init__.py
netkeiba/management/commands/backup.py
netkeiba/management/commands/import.py
netkeiba/management/commands/pipeline.py
netkeiba/management/commands/scrape.py
netkeiba/migrations/0001_initial.py
netkeiba/migrations/0002_add_models.py
netkeiba/migrations/0003_alter_race_remove_grade.py
netkeiba/migrations/0004_alter_race_race_class_choices.py
netkeiba/migrations/__init__.py
netkeiba/models/__init__.py
netkeiba/models/base.py
netkeiba/models/horse.py
netkeiba/models/jockey.py
netkeiba/models/owner.py
netkeiba/models/race.py
netkeiba/models/race_contender.py
netkeiba/models/trainer.py
netkeiba/models/webpage.py
netkeiba/parsers/__init__.py
netkeiba/parsers/noop.py
netkeiba/parsers/parser.py
netkeiba/parsers/race.py
netkeiba/spiders/__init__.py
netkeiba/spiders/db_race.py
netkeiba/spiders/race.py
netkeiba-0.0.3.dist-info/LICENSE
netkeiba-0.0.3.dist-info/METADATA
netkeiba-0.0.3.dist-info/WHEEL
netkeiba-0.0.3.dist-info/top_level.txt
netkeiba-0.0.3.dist-info/RECORD
